project/__init__.py
project/file.py
project/file1.py
Subha_DA-111.2.dist-info/LICENSE
Subha_DA-111.2.dist-info/METADATA
Subha_DA-111.2.dist-info/WHEEL
Subha_DA-111.2.dist-info/top_level.txt
Subha_DA-111.2.dist-info/RECORD
