Metadata-Version: 2.1
Name: Subha_DA
Version: 111.2
Summary: Basic arithmatic operator modules
Author: Subhaa
Author-email: subhaplatinum@gmail.com
Classifier: Programming Language :: Python :: 3
Classifier: License :: OSI Approved :: MIT License
Classifier: Operating System :: OS Independent
Requires-Python: >=3.6
License-File: LICENSE
